LICENSE
README.md
setup.cfg
setup.py
convergence/__init__.py
convergence/constants.py
convergence/convergence_service.py
convergence/database_orm.py
convergence/db_migrations/__init__.py
convergence/db_migrations/base_seed_migration_table.py
convergence/db_migrations/blueprint_formatter.py
convergence/db_migrations/migrations.py
convergence/db_migrations/structures.py
convergence/db_migrations/base/__init__.py
convergence/db_migrations/base/base_relation_formatter.py
convergence/db_migrations/base/base_seed_formatter.py
convergence/db_migrations/base/base_table_formatter.py
convergence/db_migrations/postgres/__init__.py
convergence/db_migrations/postgres/postgres_relation_formatter.py
convergence/db_migrations/postgres/postgres_seed_formatter.py
convergence/db_migrations/postgres/postgres_table_formatter.py
convergence/dto/__init__.py
convergence/dto/atomic_value.py
convergence/dto/bad_request_details.py
convergence/dto/base_dto.py
convergence/dto/service_status.py
convergence/helpers/__init__.py
convergence/helpers/base_client_service.py
convergence/helpers/controller_helpers.py
convergence/helpers/errors.py
convergence/helpers/status_controller_helper.py
convergence/internal/__init__.py
convergence/internal/db/__init__.py
convergence/internal/db/database_migrations.py
convergence/internal/observability/__init__.py
convergence/internal/observability/request_log.py
convergence/internal/observability/serializer_config.py
convergence/internal/observability/service_stdout_redirection.py
convergence/internal/observability/serializers/__init__.py
convergence/internal/observability/serializers/json_serializer.py
convergence/internal/services/__init__.py
convergence/internal/services/authentication_service.py
convergence/internal/services/base_internal_service.py
convergence/internal/services/infrastructure_service.py
convergence/internal/utils/__init__.py
convergence/internal/utils/dag.py
convergence/internal/utils/service_configuration_loader.py
convergence_service_lib.egg-info/PKG-INFO
convergence_service_lib.egg-info/SOURCES.txt
convergence_service_lib.egg-info/dependency_links.txt
convergence_service_lib.egg-info/requires.txt
convergence_service_lib.egg-info/top_level.txt