Metadata-Version: 2.1
Name: convergence-service-lib
Version: 1.0.9
Summary: The python dependency for the convergence services.
Home-page: UNKNOWN
Author: Mohammad Ali Yektaie
Author-email: ma_yektaie@outlook.com
License: UNKNOWN
Keywords: python
Platform: UNKNOWN
Classifier: Development Status :: 5 - Production/Stable
Classifier: Intended Audience :: Developers
Classifier: Programming Language :: Python :: 3
Classifier: Operating System :: Unix
Classifier: Operating System :: MacOS :: MacOS X
Classifier: Operating System :: Microsoft :: Windows
License-File: LICENSE
